SimulRPi/GPIO.py
SimulRPi/__init__.py
SimulRPi/default_keymap.py
SimulRPi/manager.py
SimulRPi/mapping.py
SimulRPi/pindb.py
SimulRPi/run_examples.py
SimulRPi/script.py
SimulRPi/test.py
SimulRPi/utils.py
SimulRPi-0.1.0a1.dist-info/LICENSE
SimulRPi-0.1.0a1.dist-info/METADATA
SimulRPi-0.1.0a1.dist-info/WHEEL
SimulRPi-0.1.0a1.dist-info/entry_points.txt
SimulRPi-0.1.0a1.dist-info/top_level.txt
SimulRPi-0.1.0a1.dist-info/RECORD
