Metadata-Version: 2.1
Name: SimulRPi
Version: 0.1.0a1
Summary: A library that partly fakes RPi.GPIO and simulates some I/O devices on a Raspberry Pi.
Home-page: https://github.com/raul23/SimulRPi
Author: Raul C.
Author-email: rchfe23@gmail.com
License: GPLv3
Project-URL: Bug Reports, https://github.com/raul23/SimulRPi/issues
Project-URL: Documentation, https://simulrpi.readthedocs.io
Project-URL: Source, https://github.com/raul23/SimulRPi
Keywords: Raspberry Pi GPIO pynput library simulation mock
Platform: UNKNOWN
Classifier: Development Status :: 3 - Alpha
Classifier: Environment :: Console
Classifier: Intended Audience :: Developers
Classifier: License :: OSI Approved :: GNU General Public License v3 (GPLv3)
Classifier: Natural Language :: English
Classifier: Operating System :: MacOS
Classifier: Operating System :: POSIX :: Linux
Classifier: Programming Language :: Python :: 3
Classifier: Topic :: Software Development :: Libraries
Classifier: Topic :: Software Development :: Libraries :: Python Modules
